pedestrian_detection_ssdlite/api.py
pedestrian_detection_ssdlite/frozen_inference_graph.pb
pedestrian_detection_ssdlite-0.2.dist-info/LICENSE
pedestrian_detection_ssdlite-0.2.dist-info/METADATA
pedestrian_detection_ssdlite-0.2.dist-info/WHEEL
pedestrian_detection_ssdlite-0.2.dist-info/top_level.txt
pedestrian_detection_ssdlite-0.2.dist-info/RECORD
