Metadata-Version: 2.1
Name: pedestrian-detection-ssdlite
Version: 0.2
Summary: UNKNOWN
Home-page: https://github.com/garyburgmann/pedestrian_detection_ssdlite
Author: Gary Burgmann
Author-email: garyburgmann@gmail.com
License: MIT
Platform: UNKNOWN
Classifier: Development Status :: 3 - Alpha
Classifier: License :: OSI Approved :: MIT License
Classifier: Programming Language :: Python :: 3.6
Requires-Dist: tensorflow (>=2)
Requires-Dist: opencv-python (>=4)
Requires-Dist: numpy
